{
	"configurations" : 
	[
		{
			"directories" : 
			[
				{
					"build" : ".",
					"minimumCMakeVersion" : 
					{
						"string" : "3.0"
					},
					"projectIndex" : 0,
					"source" : ".",
					"targetIndexes" : 
					[
						0
					]
				}
			],
			"name" : "Debug",
			"projects" : 
			[
				{
					"directoryIndexes" : 
					[
						0
					],
					"name" : "MyProject",
					"targetIndexes" : 
					[
						0
					]
				}
			],
			"targets" : 
			[
				{
					"directoryIndex" : 0,
					"id" : "mysqlTest::@6890427a1f51a3e7e1df",
					"jsonFile" : "target-mysqlTest-Debug-337e5eb958392ef9464d.json",
					"name" : "mysqlTest",
					"projectIndex" : 0
				}
			]
		}
	],
	"kind" : "codemodel",
	"paths" : 
	{
		"build" : "/home/willian12/VerilogDesign/MysqlConnectCpp/build",
		"source" : "/home/willian12/VerilogDesign/MysqlConnectCpp"
	},
	"version" : 
	{
		"major" : 2,
		"minor" : 0
	}
}
